<?xml version="1.0" encoding="UTF-8"?>
<!DOCTYPE assessment_pulmonary_function SYSTEM "assessment_pulmonary_function.dtd">
<assessment_pulmonary_function>
<id>bb0e8400-e29b-41d4-a716-446655440006</id>
<assessment_id>660e8400-e29b-41d4-a716-446655440001</assessment_id>
<spirometry_performed>yes</spirometry_performed>
<test_date>2026-01-15</test_date>
<fev1_litres>0.0</fev1_litres>
<fev1_predicted_pct>0.0</fev1_predicted_pct>
<fvc_litres>0.0</fvc_litres>
<fvc_predicted_pct>0.0</fvc_predicted_pct>
<fev1_fvc_ratio>1.5</fev1_fvc_ratio>
<peak_flow_lmin>1</peak_flow_lmin>
<peak_flow_variability_pct>0.0</peak_flow_variability_pct>
<dlco_pct>0.0</dlco_pct>
<total_lung_capacity_pct>0.0</total_lung_capacity_pct>
<residual_volume_pct>0.0</residual_volume_pct>
<bronchodilator_reversibility>yes</bronchodilator_reversibility>
<methacholine_challenge>positive</methacholine_challenge>
<oxygen_saturation_rest>1.5</oxygen_saturation_rest>
<arterial_blood_gas_performed>yes</arterial_blood_gas_performed>
<pao2_kpa>0.0</pao2_kpa>
<paco2_kpa>0.0</paco2_kpa>
<additional_notes>Example text.</additional_notes>
<created_at>2026-04-09T10:00:00Z</created_at>
<updated_at>2026-04-09T10:00:00Z</updated_at>
</assessment_pulmonary_function>
