{
  "resourceType": "Observation",
  "id": "ff0e8400-e29b-41d4-a716-44665544000a",
  "meta": {
    "profile": [
      "http://hl7.org/fhir/StructureDefinition/Observation"
    ],
    "lastUpdated": "2026-04-09T10:00:00+00:00"
  },
  "status": "final",
  "category": [
    {
      "coding": [
        {
          "system": "http://terminology.hl7.org/CodeSystem/observation-category",
          "code": "survey",
          "display": "Survey"
        }
      ]
    }
  ],
  "code": {
    "coding": [
      {
        "system": "urn:medical-forms:medical-error-report",
        "code": "assessment_corrective_actions",
        "display": "Corrective Actions"
      }
    ]
  },
  "subject": {
    "reference": "Patient/550e8400-e29b-41d4-a716-446655440000"
  },
  "encounter": {
    "reference": "Encounter/660e8400-e29b-41d4-a716-446655440001"
  },
  "effectiveDateTime": "2026-04-09T10:00:00+00:00",
  "component": [
    {
      "code": {
        "coding": [
          {
            "system": "urn:medical-forms:medical-error-report",
            "code": "immediate_corrective_actions",
            "display": "Immediate Corrective Actions"
          }
        ]
      },
      "valueString": ""
    },
    {
      "code": {
        "coding": [
          {
            "system": "urn:medical-forms:medical-error-report",
            "code": "long_term_corrective_actions",
            "display": "Long Term Corrective Actions"
          }
        ]
      },
      "valueString": ""
    },
    {
      "code": {
        "coding": [
          {
            "system": "urn:medical-forms:medical-error-report",
            "code": "policy_change_required",
            "display": "Policy Change Required"
          }
        ]
      },
      "valueCodeableConcept": {
        "coding": [
          {
            "system": "urn:medical-forms:medical-error-report:policy_change_required",
            "code": "yes",
            "display": "Yes"
          }
        ]
      }
    },
    {
      "code": {
        "coding": [
          {
            "system": "urn:medical-forms:medical-error-report",
            "code": "policy_change_details",
            "display": "Policy Change Details"
          }
        ]
      },
      "valueString": "Example text."
    },
    {
      "code": {
        "coding": [
          {
            "system": "urn:medical-forms:medical-error-report",
            "code": "training_required",
            "display": "Training Required"
          }
        ]
      },
      "valueCodeableConcept": {
        "coding": [
          {
            "system": "urn:medical-forms:medical-error-report:training_required",
            "code": "yes",
            "display": "Yes"
          }
        ]
      }
    },
    {
      "code": {
        "coding": [
          {
            "system": "urn:medical-forms:medical-error-report",
            "code": "training_details",
            "display": "Training Details"
          }
        ]
      },
      "valueString": "Example text."
    },
    {
      "code": {
        "coding": [
          {
            "system": "urn:medical-forms:medical-error-report",
            "code": "equipment_change_required",
            "display": "Equipment Change Required"
          }
        ]
      },
      "valueCodeableConcept": {
        "coding": [
          {
            "system": "urn:medical-forms:medical-error-report:equipment_change_required",
            "code": "yes",
            "display": "Yes"
          }
        ]
      }
    },
    {
      "code": {
        "coding": [
          {
            "system": "urn:medical-forms:medical-error-report",
            "code": "equipment_change_details",
            "display": "Equipment Change Details"
          }
        ]
      },
      "valueString": "Example text."
    },
    {
      "code": {
        "coding": [
          {
            "system": "urn:medical-forms:medical-error-report",
            "code": "process_redesign_required",
            "display": "Process Redesign Required"
          }
        ]
      },
      "valueCodeableConcept": {
        "coding": [
          {
            "system": "urn:medical-forms:medical-error-report:process_redesign_required",
            "code": "yes",
            "display": "Yes"
          }
        ]
      }
    },
    {
      "code": {
        "coding": [
          {
            "system": "urn:medical-forms:medical-error-report",
            "code": "process_redesign_details",
            "display": "Process Redesign Details"
          }
        ]
      },
      "valueString": "Example text."
    },
    {
      "code": {
        "coding": [
          {
            "system": "urn:medical-forms:medical-error-report",
            "code": "responsible_person",
            "display": "Responsible Person"
          }
        ]
      },
      "valueString": ""
    },
    {
      "code": {
        "coding": [
          {
            "system": "urn:medical-forms:medical-error-report",
            "code": "target_completion_date",
            "display": "Target Completion Date"
          }
        ]
      },
      "valueDateTime": "2026-01-15"
    },
    {
      "code": {
        "coding": [
          {
            "system": "urn:medical-forms:medical-error-report",
            "code": "actions_status",
            "display": "Actions Status"
          }
        ]
      },
      "valueCodeableConcept": {
        "coding": [
          {
            "system": "urn:medical-forms:medical-error-report:actions_status",
            "code": "planned",
            "display": "Planned"
          }
        ]
      }
    }
  ]
}
