<?xml version="1.0" encoding="UTF-8"?>
<!DOCTYPE assessment_organ_function SYSTEM "assessment_organ_function.dtd">
<assessment_organ_function>
<id>aa0e8400-e29b-41d4-a716-446655440005</id>
<assessment_id>660e8400-e29b-41d4-a716-446655440001</assessment_id>
<serum_creatinine>0.0</serum_creatinine>
<egfr>0.0</egfr>
<proteinuria>yes</proteinuria>
<renal_ultrasound_normal>yes</renal_ultrasound_normal>
<renal_ultrasound_findings>Example text.</renal_ultrasound_findings>
<alt>0.0</alt>
<ast>0.0</ast>
<bilirubin>0.0</bilirubin>
<albumin>0.0</albumin>
<inr>0.0</inr>
<liver_steatosis>none</liver_steatosis>
<ecg_normal>yes</ecg_normal>
<ecg_findings>Example text.</ecg_findings>
<echo_performed>yes</echo_performed>
<lvef>0.0</lvef>
<echo_findings>Example text.</echo_findings>
<troponin>0.0</troponin>
<pao2>0.0</pao2>
<fio2>0.0</fio2>
<pf_ratio>1.5</pf_ratio>
<chest_xray_normal>yes</chest_xray_normal>
<chest_xray_findings>Example text.</chest_xray_findings>
<bronchoscopy_performed>yes</bronchoscopy_performed>
<bronchoscopy_findings>Example text.</bronchoscopy_findings>
<organ_function_notes>Example text.</organ_function_notes>
<created_at>2026-04-09T10:00:00Z</created_at>
<updated_at>2026-04-09T10:00:00Z</updated_at>
</assessment_organ_function>
