{
  "resourceType": "Observation",
  "id": "ff0e8400-e29b-41d4-a716-44665544000a",
  "meta": {
    "profile": [
      "http://hl7.org/fhir/StructureDefinition/Observation"
    ],
    "lastUpdated": "2026-04-09T10:00:00+00:00"
  },
  "status": "final",
  "category": [
    {
      "coding": [
        {
          "system": "http://terminology.hl7.org/CodeSystem/observation-category",
          "code": "survey",
          "display": "Survey"
        }
      ]
    }
  ],
  "code": {
    "coding": [
      {
        "system": "urn:medical-forms:mental-health-assessment",
        "code": "assessment_treatment_history",
        "display": "Treatment History"
      }
    ]
  },
  "subject": {
    "reference": "Patient/550e8400-e29b-41d4-a716-446655440000"
  },
  "encounter": {
    "reference": "Encounter/660e8400-e29b-41d4-a716-446655440001"
  },
  "effectiveDateTime": "2026-04-09T10:00:00+00:00",
  "component": [
    {
      "code": {
        "coding": [
          {
            "system": "urn:medical-forms:mental-health-assessment",
            "code": "previous_psychiatric_diagnosis",
            "display": "Previous Psychiatric Diagnosis"
          }
        ]
      },
      "valueCodeableConcept": {
        "coding": [
          {
            "system": "urn:medical-forms:mental-health-assessment:previous_psychiatric_diagnosis",
            "code": "yes",
            "display": "Yes"
          }
        ]
      }
    },
    {
      "code": {
        "coding": [
          {
            "system": "urn:medical-forms:mental-health-assessment",
            "code": "previous_diagnoses",
            "display": "Previous Diagnoses"
          }
        ]
      },
      "valueString": ""
    },
    {
      "code": {
        "coding": [
          {
            "system": "urn:medical-forms:mental-health-assessment",
            "code": "previous_therapy",
            "display": "Previous Therapy"
          }
        ]
      },
      "valueCodeableConcept": {
        "coding": [
          {
            "system": "urn:medical-forms:mental-health-assessment:previous_therapy",
            "code": "yes",
            "display": "Yes"
          }
        ]
      }
    },
    {
      "code": {
        "coding": [
          {
            "system": "urn:medical-forms:mental-health-assessment",
            "code": "therapy_type",
            "display": "Therapy Type"
          }
        ]
      },
      "valueCodeableConcept": {
        "coding": [
          {
            "system": "urn:medical-forms:mental-health-assessment:therapy_type",
            "code": "cbt",
            "display": "Cbt"
          }
        ]
      }
    },
    {
      "code": {
        "coding": [
          {
            "system": "urn:medical-forms:mental-health-assessment",
            "code": "therapy_details",
            "display": "Therapy Details"
          }
        ]
      },
      "valueString": "Example text."
    },
    {
      "code": {
        "coding": [
          {
            "system": "urn:medical-forms:mental-health-assessment",
            "code": "previous_psychiatric_admission",
            "display": "Previous Psychiatric Admission"
          }
        ]
      },
      "valueCodeableConcept": {
        "coding": [
          {
            "system": "urn:medical-forms:mental-health-assessment:previous_psychiatric_admission",
            "code": "yes",
            "display": "Yes"
          }
        ]
      }
    },
    {
      "code": {
        "coding": [
          {
            "system": "urn:medical-forms:mental-health-assessment",
            "code": "admission_count",
            "display": "Admission Count"
          }
        ]
      },
      "valueInteger": 2
    },
    {
      "code": {
        "coding": [
          {
            "system": "urn:medical-forms:mental-health-assessment",
            "code": "admission_details",
            "display": "Admission Details"
          }
        ]
      },
      "valueString": "Example text."
    },
    {
      "code": {
        "coding": [
          {
            "system": "urn:medical-forms:mental-health-assessment",
            "code": "crisis_team_involvement",
            "display": "Crisis Team Involvement"
          }
        ]
      },
      "valueCodeableConcept": {
        "coding": [
          {
            "system": "urn:medical-forms:mental-health-assessment:crisis_team_involvement",
            "code": "yes",
            "display": "Yes"
          }
        ]
      }
    },
    {
      "code": {
        "coding": [
          {
            "system": "urn:medical-forms:mental-health-assessment",
            "code": "sectioned_under_mental_health_act",
            "display": "Sectioned Under Mental Health Act"
          }
        ]
      },
      "valueCodeableConcept": {
        "coding": [
          {
            "system": "urn:medical-forms:mental-health-assessment:sectioned_under_mental_health_act",
            "code": "yes",
            "display": "Yes"
          }
        ]
      }
    },
    {
      "code": {
        "coding": [
          {
            "system": "urn:medical-forms:mental-health-assessment",
            "code": "section_details",
            "display": "Section Details"
          }
        ]
      },
      "valueString": "Example text."
    },
    {
      "code": {
        "coding": [
          {
            "system": "urn:medical-forms:mental-health-assessment",
            "code": "electroconvulsive_therapy",
            "display": "Electroconvulsive Therapy"
          }
        ]
      },
      "valueCodeableConcept": {
        "coding": [
          {
            "system": "urn:medical-forms:mental-health-assessment:electroconvulsive_therapy",
            "code": "yes",
            "display": "Yes"
          }
        ]
      }
    },
    {
      "code": {
        "coding": [
          {
            "system": "urn:medical-forms:mental-health-assessment",
            "code": "treatment_response",
            "display": "Treatment Response"
          }
        ]
      },
      "valueString": ""
    },
    {
      "code": {
        "coding": [
          {
            "system": "urn:medical-forms:mental-health-assessment",
            "code": "treatment_history_notes",
            "display": "Treatment History Notes"
          }
        ]
      },
      "valueString": "Example text."
    }
  ]
}
