{
  "resourceType": "Observation",
  "id": "aa0e8400-e29b-41d4-a716-446655440005",
  "meta": {
    "profile": [
      "http://hl7.org/fhir/StructureDefinition/Observation"
    ],
    "lastUpdated": "2026-04-09T10:00:00+00:00"
  },
  "status": "final",
  "category": [
    {
      "coding": [
        {
          "system": "http://terminology.hl7.org/CodeSystem/observation-category",
          "code": "survey",
          "display": "Survey"
        }
      ]
    }
  ],
  "code": {
    "coding": [
      {
        "system": "urn:medical-forms:pediatric-assessment",
        "code": "assessment_immunization_status",
        "display": "Immunization Status"
      }
    ]
  },
  "subject": {
    "reference": "Patient/550e8400-e29b-41d4-a716-446655440000"
  },
  "encounter": {
    "reference": "Encounter/660e8400-e29b-41d4-a716-446655440001"
  },
  "effectiveDateTime": "2026-04-09T10:00:00+00:00",
  "component": [
    {
      "code": {
        "coding": [
          {
            "system": "urn:medical-forms:pediatric-assessment",
            "code": "immunization_up_to_date",
            "display": "Immunization Up To Date"
          }
        ]
      },
      "valueDateTime": "2026-01-15"
    },
    {
      "code": {
        "coding": [
          {
            "system": "urn:medical-forms:pediatric-assessment",
            "code": "immunization_schedule",
            "display": "Immunization Schedule"
          }
        ]
      },
      "valueCodeableConcept": {
        "coding": [
          {
            "system": "urn:medical-forms:pediatric-assessment:immunization_schedule",
            "code": "uk-nhs",
            "display": "Uk-Nhs"
          }
        ]
      }
    },
    {
      "code": {
        "coding": [
          {
            "system": "urn:medical-forms:pediatric-assessment",
            "code": "missed_vaccinations",
            "display": "Missed Vaccinations"
          }
        ]
      },
      "valueString": ""
    },
    {
      "code": {
        "coding": [
          {
            "system": "urn:medical-forms:pediatric-assessment",
            "code": "vaccine_adverse_reactions",
            "display": "Vaccine Adverse Reactions"
          }
        ]
      },
      "valueCodeableConcept": {
        "coding": [
          {
            "system": "urn:medical-forms:pediatric-assessment:vaccine_adverse_reactions",
            "code": "yes",
            "display": "Yes"
          }
        ]
      }
    },
    {
      "code": {
        "coding": [
          {
            "system": "urn:medical-forms:pediatric-assessment",
            "code": "adverse_reaction_details",
            "display": "Adverse Reaction Details"
          }
        ]
      },
      "valueString": "Example text."
    },
    {
      "code": {
        "coding": [
          {
            "system": "urn:medical-forms:pediatric-assessment",
            "code": "vaccine_exemptions",
            "display": "Vaccine Exemptions"
          }
        ]
      },
      "valueCodeableConcept": {
        "coding": [
          {
            "system": "urn:medical-forms:pediatric-assessment:vaccine_exemptions",
            "code": "yes",
            "display": "Yes"
          }
        ]
      }
    },
    {
      "code": {
        "coding": [
          {
            "system": "urn:medical-forms:pediatric-assessment",
            "code": "exemption_reason",
            "display": "Exemption Reason"
          }
        ]
      },
      "valueString": "Example text."
    },
    {
      "code": {
        "coding": [
          {
            "system": "urn:medical-forms:pediatric-assessment",
            "code": "bcg_given",
            "display": "Bcg Given"
          }
        ]
      },
      "valueCodeableConcept": {
        "coding": [
          {
            "system": "urn:medical-forms:pediatric-assessment:bcg_given",
            "code": "yes",
            "display": "Yes"
          }
        ]
      }
    },
    {
      "code": {
        "coding": [
          {
            "system": "urn:medical-forms:pediatric-assessment",
            "code": "influenza_vaccine",
            "display": "Influenza Vaccine"
          }
        ]
      },
      "valueCodeableConcept": {
        "coding": [
          {
            "system": "urn:medical-forms:pediatric-assessment:influenza_vaccine",
            "code": "yes",
            "display": "Yes"
          }
        ]
      }
    },
    {
      "code": {
        "coding": [
          {
            "system": "urn:medical-forms:pediatric-assessment",
            "code": "covid_vaccine",
            "display": "Covid Vaccine"
          }
        ]
      },
      "valueCodeableConcept": {
        "coding": [
          {
            "system": "urn:medical-forms:pediatric-assessment:covid_vaccine",
            "code": "yes",
            "display": "Yes"
          }
        ]
      }
    },
    {
      "code": {
        "coding": [
          {
            "system": "urn:medical-forms:pediatric-assessment",
            "code": "last_vaccination_date",
            "display": "Last Vaccination Date"
          }
        ]
      },
      "valueDateTime": "2026-01-15"
    },
    {
      "code": {
        "coding": [
          {
            "system": "urn:medical-forms:pediatric-assessment",
            "code": "additional_notes",
            "display": "Additional Notes"
          }
        ]
      },
      "valueString": "Example text."
    }
  ]
}
