<?xml version="1.0" encoding="UTF-8"?>
<!DOCTYPE assessment_cognitive_status SYSTEM "assessment_cognitive_status.dtd">
<assessment_cognitive_status>
<id>880e8400-e29b-41d4-a716-446655440003</id>
<assessment_id>660e8400-e29b-41d4-a716-446655440001</assessment_id>
<dementia_diagnosis>yes</dementia_diagnosis>
<dementia_type>alzheimers</dementia_type>
<dementia_stage>mild</dementia_stage>
<mmse_score>5</mmse_score>
<moca_score>5</moca_score>
<orientation_impaired>yes</orientation_impaired>
<short_term_memory_impaired>yes</short_term_memory_impaired>
<long_term_memory_impaired>yes</long_term_memory_impaired>
<communication_ability>intact</communication_ability>
<decision_making_capacity>full</decision_making_capacity>
<cognitive_status_notes>Example text.</cognitive_status_notes>
<created_at>2026-04-09T10:00:00Z</created_at>
<updated_at>2026-04-09T10:00:00Z</updated_at>
</assessment_cognitive_status>
