<?xml version="1.0" encoding="UTF-8"?>
<!DOCTYPE assessment_social_history SYSTEM "assessment_social_history.dtd">
<assessment_social_history>
<id>ff0e8400-e29b-41d4-a716-44665544000a</id>
<assessment_id>660e8400-e29b-41d4-a716-446655440001</assessment_id>
<smoking_status>never</smoking_status>
<pack_years>0.0</pack_years>
<vaping_status>never</vaping_status>
<passive_smoke_exposure>yes</passive_smoke_exposure>
<housing_type>standard</housing_type>
<housing_damp_or_mould>yes</housing_damp_or_mould>
<pets_in_home>yes</pets_in_home>
<pet_details>Example text.</pet_details>
<occupational_exposures>Teacher</occupational_exposures>
<exercise_frequency>twice daily</exercise_frequency>
<impact_on_daily_life></impact_on_daily_life>
<days_missed_work_or_school>1</days_missed_work_or_school>
<created_at>2026-04-09T10:00:00Z</created_at>
<updated_at>2026-04-09T10:00:00Z</updated_at>
</assessment_social_history>
