<?xml version="1.0" encoding="UTF-8"?>
<!DOCTYPE assessment_swallowing_oral_health SYSTEM "assessment_swallowing_oral_health.dtd">
<assessment_swallowing_oral_health>
<id>bb0e8400-e29b-41d4-a716-446655440006</id>
<assessment_id>660e8400-e29b-41d4-a716-446655440001</assessment_id>
<swallowing_difficulty>yes</swallowing_difficulty>
<dysphagia_severity>mild</dysphagia_severity>
<dysphagia_type>oropharyngeal</dysphagia_type>
<choking_episodes>yes</choking_episodes>
<coughing_during_meals>yes</coughing_during_meals>
<salt_referral>yes</salt_referral>
<dental_problems>yes</dental_problems>
<dental_problem_details>Example text.</dental_problem_details>
<dentures>yes</dentures>
<dentures_fit_well>yes</dentures_fit_well>
<oral_pain>yes</oral_pain>
<dry_mouth>yes</dry_mouth>
<oral_thrush>yes</oral_thrush>
<swallowing_oral_notes>Example text.</swallowing_oral_notes>
<created_at>2026-04-09T10:00:00Z</created_at>
<updated_at>2026-04-09T10:00:00Z</updated_at>
</assessment_swallowing_oral_health>
