<?xml version="1.0" encoding="UTF-8"?>
<!DOCTYPE assessment_ipss_questionnaire SYSTEM "assessment_ipss_questionnaire.dtd">
<assessment_ipss_questionnaire>
<id>990e8400-e29b-41d4-a716-446655440004</id>
<assessment_id>660e8400-e29b-41d4-a716-446655440001</assessment_id>
<ipss_q1_incomplete_emptying>1</ipss_q1_incomplete_emptying>
<ipss_q2_frequency>1</ipss_q2_frequency>
<ipss_q3_intermittency>1</ipss_q3_intermittency>
<ipss_q4_urgency>1</ipss_q4_urgency>
<ipss_q5_weak_stream>1</ipss_q5_weak_stream>
<ipss_q6_straining>1</ipss_q6_straining>
<ipss_q7_nocturia>1</ipss_q7_nocturia>
<created_at>2026-04-09T10:00:00Z</created_at>
<updated_at>2026-04-09T10:00:00Z</updated_at>
</assessment_ipss_questionnaire>
